easypqp/__init__.py
easypqp/convert.py
easypqp/library.py
easypqp/main.py
easypqp/openswathassaygenerator.py
easypqp/openswathdecoygenerator.py
easypqp/sage.py
easypqp/targetedfileconverter.py
easypqp/unimoddb.py
easypqp/util.py
easypqp/data/unimod.xml
easypqp-0.1.55.dist-info/licenses/LICENSE
easypqp-0.1.55.dist-info/METADATA
easypqp-0.1.55.dist-info/WHEEL
easypqp-0.1.55.dist-info/entry_points.txt
easypqp-0.1.55.dist-info/top_level.txt
easypqp-0.1.55.dist-info/RECORD
