Metadata-Version: 2.4
Name: easypqp
Version: 0.1.55
Summary: EasyPQP: Simple library generation for OpenSWATH
Author-email: George Rosenberger <gr2578@cumc.columbia.edu>
License-Expression: BSD-3-Clause
Project-URL: Homepage, https://github.com/grosenberger/easypqp
Requires-Python: >=3.9
License-File: LICENSE
Requires-Dist: numba
Requires-Dist: Click>=8.0.0
Requires-Dist: numpy==1.26.4
Requires-Dist: scipy
Requires-Dist: scikit-learn
Requires-Dist: statsmodels
Requires-Dist: pandas>=1.5.0
Requires-Dist: biopython
Requires-Dist: pyopenms>=3.3.0
Requires-Dist: matplotlib>=3.5.1
Requires-Dist: seaborn
Requires-Dist: tqdm
Provides-Extra: pyprophet
Requires-Dist: pyprophet; extra == "pyprophet"
Provides-Extra: rust
Requires-Dist: easypqp-rs>=0.1.5; extra == "rust"
Provides-Extra: all
Requires-Dist: pyprophet; extra == "all"
Requires-Dist: easypqp-rs>=0.1.5; extra == "all"
Dynamic: license-file
